drdump/__init__.py
drdump/__main__.py
drdump/builder.py
drdump/dependancies.py
drdump/drdump.py
drdump/load.py
drdump/management/__init__.py
drdump/management/commands/__init__.py
drdump/management/commands/dr_dump.py
drdump/management/commands/dr_load.py
drdump/maps/djangocms-2.json
drdump/maps/djangocms-3.json
tests/__init__.py
tests/test_dependancies.py
dr_dump-1.1.5.dist-info/LICENCE.txt
dr_dump-1.1.5.dist-info/METADATA
dr_dump-1.1.5.dist-info/WHEEL
dr_dump-1.1.5.dist-info/top_level.txt
dr_dump-1.1.5.dist-info/RECORD
